icecommercialpower/__init__.py
icecommercialpower/db/__init__.py
icecommercialpower/db/base_repository.py
icecommercialpower/feature_flags/__init__.py
icecommercialpower/feature_flags/feature_flag_helper.py
icecommercialpower/flutterwave/__init__.py
icecommercialpower/flutterwave/flutterwave.py
icecommercialpower/mailgun/__init__.py
icecommercialpower/mailgun/mailgun_handler.py
icecommercialpower/messaging/__init__.py
icecommercialpower/messaging/messaging.py
icecommercialpower/messaging/servicebus.py
icecommercialpower/observability/__init__.py
icecommercialpower/observability/func_observability.py
icecommercialpower/observability/utils.py
icecommercialpower/payments/__init__.py
icecommercialpower/payments/payment.py
icecommercialpower/sms/__init__.py
icecommercialpower/sms/dummy_sms_client.py
icecommercialpower/sms/sms_client.py
icecommercialpower/sms/termii_client.py
icecommercialpower/sms/twilio_client.py
icecommercialpower/steamaco/__init__.py
icecommercialpower/steamaco/customer_record.py
icecommercialpower/steamaco/dummy_steamaco_client.py
icecommercialpower/steamaco/errors.py
icecommercialpower/steamaco/meter_record.py
icecommercialpower/steamaco/steamaco_client.py
icecommercialpower/steamaco/transaction.py
icecommercialpower/subscription/__init__.py
icecommercialpower/subscription/subscription.py
icecommercialpower/utils/__init__.py
icecommercialpower/utils/cached_value.py
icecommercialpower/utils/payment_verification.py
ice_commercial_power-1.1.1.dist-info/METADATA
ice_commercial_power-1.1.1.dist-info/WHEEL
ice_commercial_power-1.1.1.dist-info/top_level.txt
ice_commercial_power-1.1.1.dist-info/RECORD
