Metadata-Version: 2.1
Name: ice-commercial-power
Version: 1.1.1
Summary: ICE Commercial Power
Home-page: https://github.com/IceCommercialPower/azure-function-spike-detector
Author: ICE Commercial Power
Author-email: 
Maintainer: ICE Commercial Power
Requires-Dist: pydantic ==1.8.2
Requires-Dist: azure-cosmos >=4.2.0
Requires-Dist: azure-appconfiguration >=1.3.0
Requires-Dist: azure-servicebus >=7.4.0
Requires-Dist: opencensus-extension-azure-functions >=1.0.0
Requires-Dist: opencensus-ext-requests >=0.7.6
Requires-Dist: requests >=2.25.1
Requires-Dist: twilio >=7.3.2
Requires-Dist: azure-identity ==1.7.1
